<?xml version="1.0" encoding="UTF-8"?><record_update table="sys_metadata_link">
    <sys_metadata_link action="INSERT_OR_UPDATE">
        <directory>unload</directory>
        <documentkey>69541dc86fb37100724708c6eb3ee4bc</documentkey>
        <payload><![CDATA[<?xml version="1.0" encoding="UTF-8"?><record_update table="x_caas_quality_bq_assign_matrix">
    <x_caas_quality_bq_assign_matrix action="INSERT_OR_UPDATE">
        <sys_created_by>x-rushaale</sys_created_by>
        <sys_created_on>2015-04-28 13:22:18</sys_created_on>
        <sys_id>69541dc86fb37100724708c6eb3ee4bc</sys_id>
        <sys_mod_count>6</sys_mod_count>
        <sys_updated_by>leonid.fedorovich@softline.com</sys_updated_by>
        <sys_updated_on>2019-10-22 14:03:26</sys_updated_on>
        <u_agree_list/>
        <u_bq_danger/>
        <u_bq_factory/>
        <u_bq_topic display_value="Качество продукции">9fb910a46f62d20010e00d55eb3ee497</u_bq_topic>
        <u_bq_user display_value="Eremenko Natalya V.">9a87d5d41bab73003cdfa64fad4bcb54</u_bq_user>
        <u_bq_usercity display_value="Ростов-на-Дону">8a398e566fab3100724708c6eb3ee4fc</u_bq_usercity>
        <u_bq_usergroup display_value="Качество продукции">d2d6a5316f2b3100724708c6eb3ee4bb</u_bq_usergroup>
        <u_notify_list/>
    </x_caas_quality_bq_assign_matrix>
</record_update>
]]></payload>
        <sys_class_name>sys_metadata_link</sys_class_name>
        <sys_created_by>leonid.fedorovich@softline.com</sys_created_by>
        <sys_created_on>2019-10-23 10:39:58</sys_created_on>
        <sys_id>5805d5231bec8c509c961028bd4bcba0</sys_id>
        <sys_mod_count>0</sys_mod_count>
        <sys_name>Created 2015-04-28 15:22:18</sys_name>
        <sys_package display_value="QUALITY" source="soft4">fe192e224f42b380b41f05818110c7b7</sys_package>
        <sys_policy/>
        <sys_scope display_value="QUALITY">fe192e224f42b380b41f05818110c7b7</sys_scope>
        <sys_update_name>sys_metadata_link_5805d5231bec8c509c961028bd4bcba0</sys_update_name>
        <sys_updated_by>leonid.fedorovich@softline.com</sys_updated_by>
        <sys_updated_on>2019-10-23 10:39:58</sys_updated_on>
        <tablename>x_caas_quality_bq_assign_matrix</tablename>
    </sys_metadata_link>
</record_update>
